raw_wrapper/__init__.py
raw_wrapper/raw_wrapper.py
raw_wrapper-1.0.0.dist-info/METADATA
raw_wrapper-1.0.0.dist-info/WHEEL
raw_wrapper-1.0.0.dist-info/licenses/LICENSE
raw_wrapper-1.0.0.dist-info/RECORD
